iplotter/__init__.py
iplotter/base_plotter.py
iplotter/c3_plotter.py
iplotter/chartist_plotter.py
iplotter/chartjs_plotter.py
iplotter/export.py
iplotter/google_plotter.py
iplotter/plotly_plotter.py
iplotter-0.4.3.dist-info/DESCRIPTION.rst
iplotter-0.4.3.dist-info/METADATA
iplotter-0.4.3.dist-info/RECORD
iplotter-0.4.3.dist-info/WHEEL
iplotter-0.4.3.dist-info/metadata.json
iplotter-0.4.3.dist-info/top_level.txt
