Metadata-Version: 2.0
Name: iplotter
Version: 0.4.3
Summary: JavaScript Charting for iPython/Jupyter notebooks
Home-page: https://github.com/niloch/iplotter
Author: csulliva
Author-email: csulliva@brandeis.edu
License: MIT
Keywords: ipython,plotly,c3.js,plot,chart,plotly.js,charts.js,chartist.js,jupyter
Platform: UNKNOWN
Classifier: Development Status :: 3 - Alpha
Classifier: Intended Audience :: Science/Research
Classifier: License :: OSI Approved :: MIT License
Classifier: Topic :: Scientific/Engineering :: Visualization
Classifier: Programming Language :: Python :: 2
Classifier: Programming Language :: Python :: 2.7
Classifier: Programming Language :: Python :: 3
Classifier: Programming Language :: Python :: 3.3
Classifier: Programming Language :: Python :: 3.4
Classifier: Programming Language :: Python :: 3.5
Classifier: Programming Language :: Python :: 3.6
Requires-Dist: Jinja2 (>=2.0)
Requires-Dist: ipython (>=3.0)
Requires-Dist: notebook (>=3.0)
Requires-Dist: selenium (>=3.0)
